sudoku/__init__.py
sudoku/sudoku.py
game_package-0.0.1.dist-info/METADATA
game_package-0.0.1.dist-info/WHEEL
game_package-0.0.1.dist-info/entry_points.txt
game_package-0.0.1.dist-info/top_level.txt
game_package-0.0.1.dist-info/RECORD
